theseptatimes/SeptaTimes.py
theseptatimes/__init__.py
theseptatimes/cli.py
theseptatimes-0.2.4.dist-info/LICENSE
theseptatimes-0.2.4.dist-info/WHEEL
theseptatimes-0.2.4.dist-info/entry_points.txt
theseptatimes-0.2.4.dist-info/METADATA
theseptatimes-0.2.4.dist-info/RECORD
