Metadata-Version: 2.1
Name: theseptatimes
Version: 0.2.4
Summary: A Python package to get data from the Septa API
License: MIT
Author: dotzenith
Requires-Python: >=3.9,<4.0
Classifier: License :: OSI Approved :: MIT License
Classifier: Programming Language :: Python :: 3
Classifier: Programming Language :: Python :: 3.9
Classifier: Programming Language :: Python :: 3.10
Classifier: Programming Language :: Python :: 3.11
Requires-Dist: DateTime (>=5.0,<6.0)
Requires-Dist: colorama (>=0.4.6,<0.5.0)
Requires-Dist: requests (>=2.28.2,<3.0.0)
Requires-Dist: thefuzz[speedup] (>=0.19.0,<0.20.0)
Requires-Dist: typer (>=0.7.0,<0.8.0)
